mdb_fields_cleaner/__init__.py
mdb_fields_cleaner/dataclass.py
mdb_fields_cleaner/pydantic.py
mdb_fields_cleaner-0.2.0.dist-info/LICENSE
mdb_fields_cleaner-0.2.0.dist-info/METADATA
mdb_fields_cleaner-0.2.0.dist-info/WHEEL
mdb_fields_cleaner-0.2.0.dist-info/RECORD
