Metadata-Version: 2.1
Name: mdb-fields-cleaner
Version: 0.2.0
Summary: 
Home-page: https://github.com/carlosvin/mdb-fields-cleaner
Author: Carlos Martin Sanchez
Author-email: carlos.martin-sanchez@mongodb.com
Requires-Python: >=3.10,<4.0
Classifier: Programming Language :: Python :: 3
Classifier: Programming Language :: Python :: 3.10
Classifier: Programming Language :: Python :: 3.11
Classifier: Programming Language :: Python :: 3.12
Requires-Dist: pymongo (>=4.6.1,<5.0.0)
Project-URL: Repository, https://github.com/carlosvin/mdb-fields-cleaner
